pyxarr/__init__.py
pyxarr/_pyxarr.py
pyxarr/dset_from_h5.py
pyxarr/dset_from_xr.py
pyxarr/dset_to_h5.py
pyxarr-0.3.0.dist-info/METADATA
pyxarr-0.3.0.dist-info/WHEEL
pyxarr-0.3.0.dist-info/licenses/LICENSE
pyxarr-0.3.0.dist-info/RECORD
