Metadata-Version: 2.4
Name: pyxarr
Version: 0.3.0
Summary: A light-weight class to work with multi-dimensional labeled arrays.
Project-URL: homepage, https://github.com/rmvanhees/pyxarr
Project-URL: Source, https://github.com/rmvanhees/pyxarr
Project-URL: Issue tracker, https://github.com/rmvanhees/pyxarr/issues
Author-email: Richard van Hees <R.M.van.Hees@sron.nl>
License-Expression: Apache-2.0
License-File: LICENSE
Classifier: Development Status :: 5 - Production/Stable
Classifier: Intended Audience :: Developers
Classifier: Intended Audience :: Science/Research
Classifier: Operating System :: OS Independent
Classifier: Programming Language :: Python :: 3 :: Only
Classifier: Programming Language :: Python :: 3.10
Classifier: Programming Language :: Python :: 3.11
Classifier: Programming Language :: Python :: 3.12
Classifier: Programming Language :: Python :: 3.13
Requires-Python: >=3.10
Requires-Dist: h5py>=3.9
Requires-Dist: numpy>=2.0
